{
    "f3f3099d-9ce7-4ad3-1ab1-52de711c1139": {
        "paletteKey": "FlexLayoutCol",
        "designerReference": [
            {
                "0": false,
                "_key": "style",
                "_value": "border-radius:10px;",
                "_type": "kv",
                "_attrDef": "p"
            },
            {
                "1": false,
                "_key": "class",
                "_value": "",
                "_type": "kv",
                "_attrDef": "p"
            },
            {
                "2": false,
                "_key": "fxFlex",
                "_value": "100",
                "_type": "kv",
                "_attrDef": "p"
            },
            {
                "3": false,
                "_key": "wrap",
                "_value": "",
                "_type": "a",
                "_attrDef": "p"
            },
            {
                "4": false,
                "_key": "fxLayoutGap",
                "_value": "",
                "_type": "kv",
                "_attrDef": "p"
            },
            {
                "6": false,
                "_key": "fxShow",
                "_value": "true",
                "_type": "kv",
                "_attrDef": "p"
            },
            {
                "7": false,
                "_key": "fxHide",
                "_value": "false",
                "_type": "kv",
                "_attrDef": "p"
            },
            {
                "_key": "layoutAlign",
                "_value": "center",
                "_type": "a",
                "_attrDef": "p"
            },
            {
                "_key": "pLayoutAlign",
                "_value": "center",
                "_type": "a",
                "_attrDef": "p"
            }
        ],
        "7bb1ecd4-4708-42f8-88ff-1f97c6c1960d": {
            "paletteKey": "FlexLayoutCol",
            "designerReference": [
                {
                    "0": false,
                    "_key": "style",
                    "_value": "",
                    "_type": "kv",
                    "_attrDef": "p"
                },
                {
                    "1": false,
                    "_key": "class",
                    "_value": "",
                    "_type": "kv",
                    "_attrDef": "p"
                },
                {
                    "2": false,
                    "_key": "fxFlex",
                    "_value": "100",
                    "_type": "kv",
                    "_attrDef": "p"
                },
                {
                    "3": false,
                    "_key": "wrap",
                    "_value": "",
                    "_type": "a",
                    "_attrDef": "p"
                },
                {
                    "4": false,
                    "_key": "fxLayoutGap",
                    "_value": "",
                    "_type": "kv",
                    "_attrDef": "p"
                },
                {
                    "6": false,
                    "_key": "fxShow",
                    "_value": "true",
                    "_type": "kv",
                    "_attrDef": "p"
                },
                {
                    "7": false,
                    "_key": "fxHide",
                    "_value": "false",
                    "_type": "kv",
                    "_attrDef": "p"
                },
                {
                    "_key": "layoutAlign",
                    "_value": "start",
                    "_type": "a",
                    "_attrDef": "p"
                },
                {
                    "_key": "pLayoutAlign",
                    "_value": "start",
                    "_type": "a",
                    "_attrDef": "p"
                }
            ],
            "e1238b1f-5211-c074-a953-973af10cf7dc": {
                "paletteKey": "NG-Toolbar",
                "designerReference": [
                    {
                        "0": false,
                        "_key": "style",
                        "_value": "position:fixed; top:0;left:0;z-index:10;height: 64px !important;",
                        "_type": "kv",
                        "_attrDef": "p"
                    },
                    {
                        "1": false,
                        "_key": "class",
                        "_value": "",
                        "_type": "kv",
                        "_attrDef": "p"
                    },
                    {
                        "2": false,
                        "_key": "color",
                        "_value": "primary",
                        "_type": "kv",
                        "_attrDef": "p"
                    },
                    {
                        "3": false,
                        "_key": "content",
                        "_value": "",
                        "_type": "a",
                        "_attrDef": "p"
                    }
                ],
                "8f20fa78-2a8b-350a-663b-20caaba0be55": {
                    "paletteKey": "FlexLayoutCol",
                    "designerReference": [
                        {
                            "_key": "style",
                            "_value": "",
                            "_type": "kv",
                            "_attrDef": "p"
                        },
                        {
                            "_key": "class",
                            "_value": "",
                            "_type": "kv",
                            "_attrDef": "p"
                        },
                        {
                            "_key": "fxFlex",
                            "_value": "50",
                            "_type": "kv",
                            "_attrDef": "p"
                        },
                        {
                            "_key": "fxLayoutGap",
                            "_value": "",
                            "_type": "kv",
                            "_attrDef": "p"
                        },
                        {
                            "_key": "wrap",
                            "_value": "wrap",
                            "_type": "a",
                            "_attrDef": "p"
                        },
                        {
                            "_key": "layoutAlign",
                            "_value": "start",
                            "_type": "a",
                            "_attrDef": "p"
                        },
                        {
                            "_key": "pLayoutAlign",
                            "_value": "stretch",
                            "_type": "a",
                            "_attrDef": "p"
                        },
                        {
                            "_key": "fxShow",
                            "_value": "true",
                            "_type": "kv",
                            "_attrDef": "p"
                        },
                        {
                            "_key": "fxHide",
                            "_value": "false",
                            "_type": "kv",
                            "_attrDef": "p"
                        }
                    ],
                    "55696aed-36fc-b92d-c4bd-32a67ed561ff": {
                        "paletteKey": "FlexLayoutCol",
                        "designerReference": [
                            {
                                "_key": "style",
                                "_value": "",
                                "_type": "kv",
                                "_attrDef": "p"
                            },
                            {
                                "_key": "class",
                                "_value": "",
                                "_type": "kv",
                                "_attrDef": "p"
                            },
                            {
                                "_key": "fxFlex",
                                "_value": "100",
                                "_type": "kv",
                                "_attrDef": "p"
                            },
                            {
                                "_key": "fxLayoutGap",
                                "_value": "",
                                "_type": "kv",
                                "_attrDef": "p"
                            },
                            {
                                "_key": "wrap",
                                "_value": "wrap",
                                "_type": "a",
                                "_attrDef": "p"
                            },
                            {
                                "_key": "layoutAlign",
                                "_value": "start",
                                "_type": "a",
                                "_attrDef": "p"
                            },
                            {
                                "_key": "pLayoutAlign",
                                "_value": "start",
                                "_type": "a",
                                "_attrDef": "p"
                            },
                            {
                                "_key": "fxShow",
                                "_value": "true",
                                "_type": "kv",
                                "_attrDef": "p"
                            },
                            {
                                "_key": "fxHide",
                                "_value": "false",
                                "_type": "kv",
                                "_attrDef": "p"
                            },
                            {
                                "_key": "fxHide.gt-sm",
                                "_value": "true",
                                "_type": "kv",
                                "_attrDef": "c"
                            }
                        ],
                        "0c953cea-05f3-e941-e052-dacba3610c6a": {
                            "paletteKey": "NG-icon",
                            "designerReference": [
                                {
                                    "0": false,
                                    "_key": "style",
                                    "_value": "cursor:pointer",
                                    "_type": "kv",
                                    "_attrDef": "p"
                                },
                                {
                                    "1": false,
                                    "_key": "class",
                                    "_value": "material-icons",
                                    "_type": "kv",
                                    "_attrDef": "p"
                                },
                                {
                                    "2": false,
                                    "_key": "IconName",
                                    "_value": "menu",
                                    "_type": "a",
                                    "_attrDef": "p"
                                },
                                {
                                    "3": false,
                                    "_key": "(click)",
                                    "_value": "sidenav.toggle()",
                                    "_type": "kv",
                                    "_attrDef": "c"
                                }
                            ]
                        }
                    }
                },
                "4c02b323-59e4-6b07-14cd-eac312eb47b7": {
                    "paletteKey": "FlexLayoutCol",
                    "designerReference": [
                        {
                            "_key": "style",
                            "_value": "",
                            "_type": "kv",
                            "_attrDef": "p"
                        },
                        {
                            "_key": "class",
                            "_value": "",
                            "_type": "kv",
                            "_attrDef": "p"
                        },
                        {
                            "_key": "fxFlex",
                            "_value": "50",
                            "_type": "kv",
                            "_attrDef": "p"
                        },
                        {
                            "_key": "fxLayoutGap",
                            "_value": "",
                            "_type": "kv",
                            "_attrDef": "p"
                        },
                        {
                            "_key": "wrap",
                            "_value": "wrap",
                            "_type": "a",
                            "_attrDef": "p"
                        },
                        {
                            "_key": "layoutAlign",
                            "_value": "end",
                            "_type": "a",
                            "_attrDef": "p"
                        },
                        {
                            "_key": "pLayoutAlign",
                            "_value": "end",
                            "_type": "a",
                            "_attrDef": "p"
                        },
                        {
                            "_key": "fxShow",
                            "_value": "true",
                            "_type": "kv",
                            "_attrDef": "p"
                        },
                        {
                            "_key": "fxHide",
                            "_value": "false",
                            "_type": "kv",
                            "_attrDef": "p"
                        }
                    ],
                    "cc3e4f47-363c-6faf-6576-d2824c37e256": {
                        "paletteKey": "NG-icon",
                        "designerReference": [
                            {
                                "_key": "style",
                                "_value": "cursor:pointer;",
                                "_type": "kv",
                                "_attrDef": "p"
                            },
                            {
                                "_key": "class",
                                "_value": "",
                                "_type": "kv",
                                "_attrDef": "p"
                            },
                            {
                                "_key": "IconName",
                                "_value": "power_settings_new",
                                "_type": "a",
                                "_attrDef": "p"
                            },
                            {
                                "_key": "(click)",
                                "_value": "logout()",
                                "_type": "kv",
                                "_attrDef": "c"
                            }
                        ]
                    }
                }
            }
        },
        "5459a2f0-9f70-be9c-7f84-84787d0dd2ad": {
            "paletteKey": "FlexLayoutCol",
            "designerReference": [
                {
                    "_key": "style",
                    "_value": "",
                    "_type": "kv",
                    "_attrDef": "p"
                },
                {
                    "_key": "class",
                    "_value": "",
                    "_type": "kv",
                    "_attrDef": "p"
                },
                {
                    "_key": "fxFlex",
                    "_value": "height:calc(100%-128px)",
                    "_type": "kv",
                    "_attrDef": "p"
                },
                {
                    "_key": "fxLayoutGap",
                    "_value": "",
                    "_type": "kv",
                    "_attrDef": "p"
                },
                {
                    "_key": "wrap",
                    "_value": "wrap",
                    "_type": "a",
                    "_attrDef": "p"
                },
                {
                    "_key": "layoutAlign",
                    "_value": "start",
                    "_type": "a",
                    "_attrDef": "p"
                },
                {
                    "_key": "pLayoutAlign",
                    "_value": "stretch",
                    "_type": "a",
                    "_attrDef": "p"
                },
                {
                    "_key": "fxShow",
                    "_value": "true",
                    "_type": "kv",
                    "_attrDef": "p"
                },
                {
                    "_key": "fxHide",
                    "_value": "false",
                    "_type": "kv",
                    "_attrDef": "p"
                }
            ],
            "f18b2cf8-176d-8697-0cc1-2c02502bfc28": {
                "paletteKey": "NG-sidenav-container",
                "designerReference": [
                    {
                        "0": false,
                        "_key": "style",
                        "_value": "top: 64px; left: 0px;position: absolute; ",
                        "_type": "kv",
                        "_attrDef": "p"
                    },
                    {
                        "1": false,
                        "_key": "class",
                        "_value": "",
                        "_type": "kv",
                        "_attrDef": "p"
                    },
                    {
                        "_key": "[ngStyle.xs]",
                        "_value": "{'margin-top':'0px '}",
                        "_type": "kv",
                        "_attrDef": "c"
                    },
                    {
                        "_key": "fullscreen",
                        "_value": "fullscreen",
                        "_type": "a",
                        "_attrDef": "c"
                    }
                ],
                "48aa2a92-7fef-cc41-5aac-074ebb26782d": {
                    "paletteKey": "NG-sidenav",
                    "designerReference": [
                        {
                            "0": false,
                            "_key": "style",
                            "_value": "",
                            "_type": "kv",
                            "_attrDef": "p"
                        },
                        {
                            "1": false,
                            "_key": "class",
                            "_value": "side-menu",
                            "_type": "kv",
                            "_attrDef": "p"
                        },
                        {
                            "2": false,
                            "_key": "mode",
                            "_value": "",
                            "_type": "kv",
                            "_attrDef": "p"
                        },
                        {
                            "3": false,
                            "_key": "opened",
                            "_value": "",
                            "_type": "kv",
                            "_attrDef": "p"
                        },
                        {
                            "4": false,
                            "_key": "align",
                            "_value": "",
                            "_type": "kv",
                            "_attrDef": "p"
                        },
                        {
                            "5": false,
                            "_key": "fxLayout",
                            "_value": "",
                            "_type": "kv",
                            "_attrDef": "p"
                        },
                        {
                            "6": false,
                            "_key": "(open)",
                            "_value": "true",
                            "_type": "kv",
                            "_attrDef": "p"
                        },
                        {
                            "7": false,
                            "_key": "(close)",
                            "_value": "",
                            "_type": "kv",
                            "_attrDef": "p"
                        },
                        {
                            "8": false,
                            "_key": "(toggle)",
                            "_value": "sidenav.toggle()",
                            "_type": "kv",
                            "_attrDef": "p"
                        },
                        {
                            "_key": "(closed)",
                            "_value": "",
                            "_type": "kv",
                            "_attrDef": "p"
                        },
                        {
                            "_key": "(opened)",
                            "_value": "opened",
                            "_type": "kv",
                            "_attrDef": "p"
                        },
                        {
                            "_key": "position",
                            "_value": "",
                            "_type": "kv",
                            "_attrDef": "p"
                        },
                        {
                            "_key": "[mode]",
                            "_value": "modeVal",
                            "_type": "kv",
                            "_attrDef": "c"
                        },
                        {
                            "_key": "[opened]",
                            "_value": "opened",
                            "_type": "kv",
                            "_attrDef": "c"
                        },
                        {
                            "_key": "[fixedInViewport]",
                            "_value": "fixedSideNav",
                            "_type": "kv",
                            "_attrDef": "c"
                        },
                        {
                            "_key": "[ngStyle.lt-md]",
                            "_value": "{'margin-top':'0px '}",
                            "_type": "kv",
                            "_attrDef": "c"
                        }
                    ],
                    "e0f9dc15-c297-454c-5b74-50dc9500492a": {
                        "paletteKey": "FlexLayoutCol",
                        "designerReference": [
                            {
                                "_key": "style",
                                "_value": "",
                                "_type": "kv",
                                "_attrDef": "p"
                            },
                            {
                                "_key": "class",
                                "_value": "",
                                "_type": "kv",
                                "_attrDef": "p"
                            },
                            {
                                "_key": "fxFlex",
                                "_value": "",
                                "_type": "kv",
                                "_attrDef": "p"
                            },
                            {
                                "_key": "fxLayoutGap",
                                "_value": "",
                                "_type": "kv",
                                "_attrDef": "p"
                            },
                            {
                                "_key": "wrap",
                                "_value": "wrap",
                                "_type": "a",
                                "_attrDef": "p"
                            },
                            {
                                "_key": "layoutAlign",
                                "_value": "start",
                                "_type": "a",
                                "_attrDef": "p"
                            },
                            {
                                "_key": "pLayoutAlign",
                                "_value": "stretch",
                                "_type": "a",
                                "_attrDef": "p"
                            },
                            {
                                "_key": "fxShow",
                                "_value": "true",
                                "_type": "kv",
                                "_attrDef": "p"
                            },
                            {
                                "_key": "fxHide",
                                "_value": "false",
                                "_type": "kv",
                                "_attrDef": "p"
                            }
                        ],
                        "4d2e514e-ecda-4d44-09b8-b92f98926e7e": {
                            "paletteKey": "FlexLayoutCol",
                            "designerReference": [
                                {
                                    "0": false,
                                    "_key": "style",
                                    "_value": "",
                                    "_type": "kv",
                                    "_attrDef": "p"
                                },
                                {
                                    "1": false,
                                    "_key": "class",
                                    "_value": "",
                                    "_type": "kv",
                                    "_attrDef": "p"
                                },
                                {
                                    "2": false,
                                    "_key": "fxFlex",
                                    "_value": "",
                                    "_type": "kv",
                                    "_attrDef": "p"
                                },
                                {
                                    "_key": "wrap",
                                    "_value": "",
                                    "_type": "a",
                                    "_attrDef": "p"
                                },
                                {
                                    "_key": "fxLayoutGap",
                                    "_value": "",
                                    "_type": "kv",
                                    "_attrDef": "p"
                                },
                                {
                                    "6": false,
                                    "_key": "fxShow",
                                    "_value": "true",
                                    "_type": "kv",
                                    "_attrDef": "p"
                                },
                                {
                                    "_key": "fxHide",
                                    "_value": "false",
                                    "_type": "kv",
                                    "_attrDef": "p"
                                },
                                {
                                    "_key": "layoutAlign",
                                    "_value": "center",
                                    "_type": "a",
                                    "_attrDef": "p"
                                },
                                {
                                    "_key": "pLayoutAlign",
                                    "_value": "center",
                                    "_type": "a",
                                    "_attrDef": "p"
                                }
                            ],
                            "56bb1e33-7f4d-3f0e-21f5-69983f6ba5c8": {
                                "paletteKey": "NG-CardImage",
                                "designerReference": [
                                    {
                                        "0": false,
                                        "_key": "style",
                                        "_value": "",
                                        "_type": "kv",
                                        "_attrDef": "p"
                                    },
                                    {
                                        "1": false,
                                        "_key": "class",
                                        "_value": "profile-user-image",
                                        "_type": "kv",
                                        "_attrDef": "p"
                                    },
                                    {
                                        "2": false,
                                        "_key": "alt",
                                        "_value": "",
                                        "_type": "kv",
                                        "_attrDef": "p"
                                    },
                                    {
                                        "3": false,
                                        "_key": "imgSrc",
                                        "_value": "user.jpg",
                                        "_type": "kv",
                                        "_attrDef": "p"
                                    }
                                ]
                            },
                            "d3f1124c-83ad-90e8-1237-ff8e2f95b117": {
                                "paletteKey": "NG-H4",
                                "designerReference": [
                                    {
                                        "0": false,
                                        "_key": "style",
                                        "_value": "font-family: 'Inconsolata', monospace;    margin: 5px 0 0px 0px;",
                                        "_type": "kv",
                                        "_attrDef": "p"
                                    },
                                    {
                                        "1": false,
                                        "_key": "class",
                                        "_value": "",
                                        "_type": "kv",
                                        "_attrDef": "p"
                                    },
                                    {
                                        "2": false,
                                        "_key": "H4 Text",
                                        "_value": "{{user}}",
                                        "_type": "a",
                                        "_attrDef": "p"
                                    }
                                ]
                            },
                            "cb7939a3-339d-06f3-3646-5dfd85c1ab46": {
                                "paletteKey": "NG-Paragraph",
                                "designerReference": [
                                    {
                                        "0": false,
                                        "_key": "style",
                                        "_value": "font-family: 'Inconsolata', monospace; margin: 0px 0 10px 0;",
                                        "_type": "kv",
                                        "_attrDef": "p"
                                    },
                                    {
                                        "1": false,
                                        "_key": "class",
                                        "_value": "",
                                        "_type": "kv",
                                        "_attrDef": "p"
                                    },
                                    {
                                        "2": false,
                                        "_key": "text",
                                        "_value": "{{numOfImages}}  Files",
                                        "_type": "a",
                                        "_attrDef": "p"
                                    }
                                ]
                            }
                        }
                    },
                    "8929a6bb-043d-6682-e951-ad2a2c6e2655": {
                        "paletteKey": "FlexLayoutCol",
                        "designerReference": [
                            {
                                "0": false,
                                "_key": "style",
                                "_value": "overflo-y:auto;",
                                "_type": "kv",
                                "_attrDef": "p"
                            },
                            {
                                "1": false,
                                "_key": "class",
                                "_value": "",
                                "_type": "kv",
                                "_attrDef": "p"
                            },
                            {
                                "2": false,
                                "_key": "fxFlex",
                                "_value": "calc(100%-300px)",
                                "_type": "kv",
                                "_attrDef": "p"
                            },
                            {
                                "3": false,
                                "_key": "wrap",
                                "_value": "",
                                "_type": "a",
                                "_attrDef": "p"
                            },
                            {
                                "4": false,
                                "_key": "fxLayoutGap",
                                "_value": ".75em",
                                "_type": "kv",
                                "_attrDef": "p"
                            },
                            {
                                "6": false,
                                "_key": "fxShow",
                                "_value": "true",
                                "_type": "kv",
                                "_attrDef": "p"
                            },
                            {
                                "7": false,
                                "_key": "fxHide",
                                "_value": "false",
                                "_type": "kv",
                                "_attrDef": "p"
                            },
                            {
                                "_key": "layoutAlign",
                                "_value": "start",
                                "_type": "a",
                                "_attrDef": "p"
                            },
                            {
                                "_key": "pLayoutAlign",
                                "_value": "center",
                                "_type": "a",
                                "_attrDef": "p"
                            }
                        ],
                        "65f816b0-b98d-5818-07f7-ea2dffb47640": {
                            "paletteKey": "FlexLayoutCol",
                            "designerReference": [
                                {
                                    "_key": "style",
                                    "_value": "",
                                    "_type": "kv",
                                    "_attrDef": "p"
                                },
                                {
                                    "_key": "class",
                                    "_value": "",
                                    "_type": "kv",
                                    "_attrDef": "p"
                                },
                                {
                                    "_key": "fxFlex",
                                    "_value": "",
                                    "_type": "kv",
                                    "_attrDef": "p"
                                },
                                {
                                    "_key": "fxLayoutGap",
                                    "_value": "",
                                    "_type": "kv",
                                    "_attrDef": "p"
                                },
                                {
                                    "_key": "wrap",
                                    "_value": "wrap",
                                    "_type": "a",
                                    "_attrDef": "p"
                                },
                                {
                                    "_key": "layoutAlign",
                                    "_value": "center",
                                    "_type": "a",
                                    "_attrDef": "p"
                                },
                                {
                                    "_key": "pLayoutAlign",
                                    "_value": "center",
                                    "_type": "a",
                                    "_attrDef": "p"
                                },
                                {
                                    "_key": "fxShow",
                                    "_value": "true",
                                    "_type": "kv",
                                    "_attrDef": "p"
                                },
                                {
                                    "_key": "fxHide",
                                    "_value": "false",
                                    "_type": "kv",
                                    "_attrDef": "p"
                                }
                            ],
                            "22d7785e-e713-076b-ae3d-cc7b9a2cde45": {
                                "paletteKey": "NG-button",
                                "designerReference": [
                                    {
                                        "_key": "style",
                                        "_value": "",
                                        "_type": "kv",
                                        "_attrDef": "p"
                                    },
                                    {
                                        "_key": "class",
                                        "_value": "uploadButton",
                                        "_type": "kv",
                                        "_attrDef": "p"
                                    },
                                    {
                                        "_key": "buttonname",
                                        "_value": "Upload",
                                        "_type": "a",
                                        "_attrDef": "p"
                                    },
                                    {
                                        "_key": "color",
                                        "_value": "accent",
                                        "_type": "kv",
                                        "_attrDef": "p"
                                    },
                                    {
                                        "_key": "(click)",
                                        "_value": "",
                                        "_type": "kv",
                                        "_attrDef": "p"
                                    }
                                ]
                            }
                        },
                        "6c3d4a6d-7635-087d-366c-0171337a7893": {
                            "paletteKey": "FlexLayoutCol",
                            "designerReference": [
                                {
                                    "0": false,
                                    "_key": "style",
                                    "_value": "width:100%;margin-top: -20px;",
                                    "_type": "kv",
                                    "_attrDef": "p"
                                },
                                {
                                    "1": false,
                                    "_key": "class",
                                    "_value": "",
                                    "_type": "kv",
                                    "_attrDef": "p"
                                },
                                {
                                    "2": false,
                                    "_key": "fxFlex",
                                    "_value": "",
                                    "_type": "kv",
                                    "_attrDef": "p"
                                },
                                {
                                    "3": false,
                                    "_key": "wrap",
                                    "_value": "",
                                    "_type": "a",
                                    "_attrDef": "p"
                                },
                                {
                                    "4": false,
                                    "_key": "fxLayoutGap",
                                    "_value": "",
                                    "_type": "kv",
                                    "_attrDef": "p"
                                },
                                {
                                    "6": false,
                                    "_key": "fxShow",
                                    "_value": "true",
                                    "_type": "kv",
                                    "_attrDef": "p"
                                },
                                {
                                    "7": false,
                                    "_key": "fxHide",
                                    "_value": "false",
                                    "_type": "kv",
                                    "_attrDef": "p"
                                },
                                {
                                    "_key": "layoutAlign",
                                    "_value": "start",
                                    "_type": "a",
                                    "_attrDef": "p"
                                },
                                {
                                    "_key": "pLayoutAlign",
                                    "_value": "start",
                                    "_type": "a",
                                    "_attrDef": "p"
                                }
                            ],
                            "2d9774fe-7ef3-75ee-d00b-1413d3307be4": {
                                "paletteKey": "NG-icon",
                                "designerReference": [
                                    {
                                        "0": false,
                                        "_key": "style",
                                        "_value": "",
                                        "_type": "kv",
                                        "_attrDef": "p"
                                    },
                                    {
                                        "1": false,
                                        "_key": "class",
                                        "_value": "mat-icon-Search",
                                        "_type": "kv",
                                        "_attrDef": "p"
                                    },
                                    {
                                        "2": false,
                                        "_key": "IconName",
                                        "_value": "search",
                                        "_type": "a",
                                        "_attrDef": "p"
                                    }
                                ]
                            },
                            "cdfe04ce-40d1-3494-0210-7498af8d6949": {
                                "paletteKey": "NG-Input",
                                "designerReference": [
                                    {
                                        "0": false,
                                        "_key": "style",
                                        "_value": "  ",
                                        "_type": "kv",
                                        "_attrDef": "p"
                                    },
                                    {
                                        "1": false,
                                        "_key": "class",
                                        "_value": "side-nav-search-input",
                                        "_type": "kv",
                                        "_attrDef": "p"
                                    },
                                    {
                                        "2": false,
                                        "_key": "placeholder",
                                        "_value": "",
                                        "_type": "kv",
                                        "_attrDef": "p"
                                    },
                                    {
                                        "3": false,
                                        "_key": "value",
                                        "_value": "",
                                        "_type": "kv",
                                        "_attrDef": "p"
                                    },
                                    {
                                        "4": false,
                                        "_key": "required",
                                        "_value": "",
                                        "_type": "a",
                                        "_attrDef": "p"
                                    },
                                    {
                                        "5": false,
                                        "_key": "[(ngModel)]",
                                        "_value": "text",
                                        "_type": "kv",
                                        "_attrDef": "p"
                                    },
                                    {
                                        "6": false,
                                        "_key": "color",
                                        "_value": "",
                                        "_type": "kv",
                                        "_attrDef": "p"
                                    },
                                    {
                                        "7": false,
                                        "_key": "name",
                                        "_value": "",
                                        "_type": "kv",
                                        "_attrDef": "p"
                                    },
                                    {
                                        "8": false,
                                        "_key": "type",
                                        "_value": "text",
                                        "_type": "kv",
                                        "_attrDef": "p"
                                    },
                                    {
                                        "9": false,
                                        "_key": "(click)",
                                        "_value": "textClick()",
                                        "_type": "kv",
                                        "_attrDef": "c"
                                    }
                                ]
                            }
                        },
                        "2e0db6d1-f2da-aba1-64ec-e629f0932c06": {
                            "paletteKey": "FlexLayoutCol",
                            "designerReference": [
                                {
                                    "0": false,
                                    "_key": "style",
                                    "_value": "width:100%",
                                    "_type": "kv",
                                    "_attrDef": "p"
                                },
                                {
                                    "1": false,
                                    "_key": "class",
                                    "_value": "",
                                    "_type": "kv",
                                    "_attrDef": "p"
                                },
                                {
                                    "_key": "fxFlex",
                                    "_value": "",
                                    "_type": "kv",
                                    "_attrDef": "p"
                                },
                                {
                                    "_key": "wrap",
                                    "_value": "",
                                    "_type": "a",
                                    "_attrDef": "p"
                                },
                                {
                                    "4": false,
                                    "_key": "fxLayoutGap",
                                    "_value": "",
                                    "_type": "kv",
                                    "_attrDef": "p"
                                },
                                {
                                    "_key": "layoutAlign",
                                    "_value": "",
                                    "_type": "a",
                                    "_attrDef": "p"
                                },
                                {
                                    "_key": "fxShow",
                                    "_value": "true",
                                    "_type": "kv",
                                    "_attrDef": "p"
                                },
                                {
                                    "_key": "fxHide",
                                    "_value": "false",
                                    "_type": "kv",
                                    "_attrDef": "p"
                                },
                                {
                                    "_key": "pLayoutAlign",
                                    "_value": "",
                                    "_type": "a",
                                    "_attrDef": "p"
                                }
                            ],
                            "37943548-5fc0-55c6-47bb-0afeee3a1edd": {
                                "paletteKey": "NG-Paragraph",
                                "designerReference": [
                                    {
                                        "0": false,
                                        "_key": "style",
                                        "_value": "padding-left:8px; font-size:14px;font-family: 'Inconsolata', monospace; font-weight:bold;margin: 2px 0 6px 0;",
                                        "_type": "kv",
                                        "_attrDef": "p"
                                    },
                                    {
                                        "1": false,
                                        "_key": "class",
                                        "_value": "",
                                        "_type": "kv",
                                        "_attrDef": "p"
                                    },
                                    {
                                        "2": false,
                                        "_key": "text",
                                        "_value": "CATEGORIES",
                                        "_type": "a",
                                        "_attrDef": "p"
                                    }
                                ]
                            },
                            "85dcaadf-67a4-f3cd-512c-cb17cea86150": {
                                "paletteKey": "NG-options-toggle-widget",
                                "designerReference": [
                                    {
                                        "_key": "style",
                                        "_value": "",
                                        "_type": "kv",
                                        "_attrDef": "p"
                                    },
                                    {
                                        "_key": "class",
                                        "_value": "",
                                        "_type": "kv",
                                        "_attrDef": "p"
                                    },
                                    {
                                        "_key": "[toggleOptions]",
                                        "_value": "button",
                                        "_type": "kv",
                                        "_attrDef": "p"
                                    },
                                    {
                                        "_key": "[align]",
                                        "_value": "'vertical'",
                                        "_type": "kv",
                                        "_attrDef": "p"
                                    },
                                    {
                                        "_key": "[disabledIndex]",
                                        "_value": "",
                                        "_type": "kv",
                                        "_attrDef": "p"
                                    },
                                    {
                                        "_key": "[checkedIndex]",
                                        "_value": "",
                                        "_type": "kv",
                                        "_attrDef": "p"
                                    },
                                    {
                                        "_key": "(indexChange)",
                                        "_value": "",
                                        "_type": "kv",
                                        "_attrDef": "p"
                                    },
                                    {
                                        "_key": "(valueChange)",
                                        "_value": "menubtn2($event)",
                                        "_type": "kv",
                                        "_attrDef": "p"
                                    }
                                ]
                            }
                        },
                        "bee749a2-1d9d-bbf1-5140-e80147449b24": {
                            "paletteKey": "FlexLayoutRow",
                            "designerReference": [
                                {
                                    "_key": "style",
                                    "_value": "position:fixed; bottom:80px;",
                                    "_type": "kv",
                                    "_attrDef": "p"
                                },
                                {
                                    "_key": "class",
                                    "_value": "",
                                    "_type": "kv",
                                    "_attrDef": "p"
                                },
                                {
                                    "_key": "fxFlex",
                                    "_value": "100",
                                    "_type": "kv",
                                    "_attrDef": "p"
                                },
                                {
                                    "_key": "fxLayoutGap",
                                    "_value": "",
                                    "_type": "kv",
                                    "_attrDef": "p"
                                },
                                {
                                    "_key": "wrap",
                                    "_value": "wrap",
                                    "_type": "a",
                                    "_attrDef": "p"
                                },
                                {
                                    "_key": "layoutAlign",
                                    "_value": "start",
                                    "_type": "a",
                                    "_attrDef": "p"
                                },
                                {
                                    "_key": "pLayoutAlign",
                                    "_value": "start",
                                    "_type": "a",
                                    "_attrDef": "p"
                                },
                                {
                                    "_key": "fxShow",
                                    "_value": "true",
                                    "_type": "kv",
                                    "_attrDef": "p"
                                },
                                {
                                    "_key": "fxHide",
                                    "_value": "false",
                                    "_type": "kv",
                                    "_attrDef": "p"
                                },
                                {
                                    "_key": "fxHide.lt-md",
                                    "_value": "true",
                                    "_type": "kv",
                                    "_attrDef": "c"
                                }
                            ],
                            "229e983d-cfbb-94f6-96d1-d9196e89f774": {
                                "paletteKey": "NG-icon",
                                "designerReference": [
                                    {
                                        "_key": "style",
                                        "_value": "color:red;cursor:pointer",
                                        "_type": "kv",
                                        "_attrDef": "p"
                                    },
                                    {
                                        "_key": "class",
                                        "_value": "zoom_out",
                                        "_type": "kv",
                                        "_attrDef": "p"
                                    },
                                    {
                                        "_key": "IconName",
                                        "_value": "remove_circle",
                                        "_type": "a",
                                        "_attrDef": "p"
                                    },
                                    {
                                        "_key": "(click)",
                                        "_value": "gridSub()",
                                        "_type": "kv",
                                        "_attrDef": "c"
                                    },
                                    {
                                        "_key": "title",
                                        "_value": "Zoom out",
                                        "_type": "kv",
                                        "_attrDef": "c"
                                    }
                                ]
                            },
                            "5ca62a00-c32a-dd15-0b48-7c1573586af7": {
                                "paletteKey": "NG-Slider",
                                "designerReference": [
                                    {
                                        "_key": "style",
                                        "_value": "",
                                        "_type": "kv",
                                        "_attrDef": "p"
                                    },
                                    {
                                        "_key": "class",
                                        "_value": "zoom-slider",
                                        "_type": "kv",
                                        "_attrDef": "p"
                                    },
                                    {
                                        "_key": "[(ngModel)]",
                                        "_value": "gridval",
                                        "_type": "kv",
                                        "_attrDef": "p"
                                    },
                                    {
                                        "_key": "color",
                                        "_value": "warn",
                                        "_type": "kv",
                                        "_attrDef": "p"
                                    },
                                    {
                                        "_key": "invert",
                                        "_value": "",
                                        "_type": "kv",
                                        "_attrDef": "p"
                                    },
                                    {
                                        "_key": "max",
                                        "_value": "100",
                                        "_type": "kv",
                                        "_attrDef": "p"
                                    },
                                    {
                                        "_key": "min",
                                        "_value": "0",
                                        "_type": "kv",
                                        "_attrDef": "p"
                                    },
                                    {
                                        "_key": "step",
                                        "_value": "20",
                                        "_type": "kv",
                                        "_attrDef": "p"
                                    },
                                    {
                                        "_key": "thumbLabel",
                                        "_value": "",
                                        "_type": "kv",
                                        "_attrDef": "p"
                                    },
                                    {
                                        "_key": "vertical",
                                        "_value": "",
                                        "_type": "kv",
                                        "_attrDef": "p"
                                    },
                                    {
                                        "_key": "disabled",
                                        "_value": "",
                                        "_type": "kv",
                                        "_attrDef": "p"
                                    },
                                    {
                                        "_key": "value",
                                        "_value": "{{gridval}}",
                                        "_type": "kv",
                                        "_attrDef": "p"
                                    },
                                    {
                                        "_key": "(change)",
                                        "_value": "",
                                        "_type": "kv",
                                        "_attrDef": "p"
                                    },
                                    {
                                        "_key": "(input)",
                                        "_value": "",
                                        "_type": "kv",
                                        "_attrDef": "p"
                                    },
                                    {
                                        "_key": "(click)",
                                        "_value": "forZoom();",
                                        "_type": "kv",
                                        "_attrDef": "c"
                                    }
                                ]
                            },
                            "1edd2505-2137-ee70-12b0-8ee43f282f96": {
                                "paletteKey": "NG-icon",
                                "designerReference": [
                                    {
                                        "_key": "style",
                                        "_value": "color:red;cursor:pointer",
                                        "_type": "kv",
                                        "_attrDef": "p"
                                    },
                                    {
                                        "_key": "class",
                                        "_value": "zoom_in",
                                        "_type": "kv",
                                        "_attrDef": "p"
                                    },
                                    {
                                        "_key": "IconName",
                                        "_value": "add_circle",
                                        "_type": "a",
                                        "_attrDef": "p"
                                    },
                                    {
                                        "_key": "(click)",
                                        "_value": "gridAdd()",
                                        "_type": "kv",
                                        "_attrDef": "c"
                                    },
                                    {
                                        "_key": "title",
                                        "_value": "Zoom in",
                                        "_type": "kv",
                                        "_attrDef": "c"
                                    }
                                ]
                            }
                        }
                    }
                },
                "10e277a4-e00b-8027-8963-02db9d379fd5": {
                    "paletteKey": "FlexLayoutCol",
                    "designerReference": [
                        {
                            "_key": "style",
                            "_value": "margin-bottom:30px",
                            "_type": "kv",
                            "_attrDef": "p"
                        },
                        {
                            "_key": "class",
                            "_value": "",
                            "_type": "kv",
                            "_attrDef": "p"
                        },
                        {
                            "_key": "fxFlex",
                            "_value": "",
                            "_type": "kv",
                            "_attrDef": "p"
                        },
                        {
                            "_key": "fxLayoutGap",
                            "_value": "",
                            "_type": "kv",
                            "_attrDef": "p"
                        },
                        {
                            "_key": "wrap",
                            "_value": "wrap",
                            "_type": "a",
                            "_attrDef": "p"
                        },
                        {
                            "_key": "layoutAlign",
                            "_value": "space-around",
                            "_type": "a",
                            "_attrDef": "p"
                        },
                        {
                            "_key": "pLayoutAlign",
                            "_value": "none",
                            "_type": "a",
                            "_attrDef": "p"
                        },
                        {
                            "_key": "fxShow",
                            "_value": "true",
                            "_type": "kv",
                            "_attrDef": "p"
                        },
                        {
                            "_key": "fxHide",
                            "_value": "false",
                            "_type": "kv",
                            "_attrDef": "p"
                        }
                    ],
                    "f85c1a35-80a8-6b18-d47f-5f43357958d8": {
                        "paletteKey": "FlexLayoutCol",
                        "designerReference": [
                            {
                                "0": false,
                                "_key": "style",
                                "_value": "margin: 0 0 0px 30px;",
                                "_type": "kv",
                                "_attrDef": "p"
                            },
                            {
                                "1": false,
                                "_key": "class",
                                "_value": "",
                                "_type": "kv",
                                "_attrDef": "p"
                            },
                            {
                                "2": false,
                                "_key": "fxFlex",
                                "_value": "100",
                                "_type": "kv",
                                "_attrDef": "p"
                            },
                            {
                                "3": false,
                                "_key": "wrap",
                                "_value": "wrap",
                                "_type": "a",
                                "_attrDef": "p"
                            },
                            {
                                "4": false,
                                "_key": "fxLayoutGap",
                                "_value": "20px",
                                "_type": "kv",
                                "_attrDef": "p"
                            },
                            {
                                "6": false,
                                "_key": "fxShow",
                                "_value": "true",
                                "_type": "kv",
                                "_attrDef": "p"
                            },
                            {
                                "7": false,
                                "_key": "fxHide",
                                "_value": "false",
                                "_type": "kv",
                                "_attrDef": "p"
                            },
                            {
                                "_key": "layoutAlign",
                                "_value": "start",
                                "_type": "a",
                                "_attrDef": "p"
                            },
                            {
                                "_key": "pLayoutAlign",
                                "_value": "start",
                                "_type": "a",
                                "_attrDef": "p"
                            },
                            {
                                "_key": "*ngFor",
                                "_value": "let image of arrayLists; let i = index",
                                "_type": "kv",
                                "_attrDef": "c"
                            }
                        ],
                        "e29b7d66-1f20-3fcc-7991-a6e222084624": {
                            "paletteKey": "NG-H3",
                            "designerReference": [
                                {
                                    "0": false,
                                    "_key": "style",
                                    "_value": "",
                                    "_type": "kv",
                                    "_attrDef": "p"
                                },
                                {
                                    "1": false,
                                    "_key": "class",
                                    "_value": "albumNameHeading",
                                    "_type": "kv",
                                    "_attrDef": "p"
                                },
                                {
                                    "2": false,
                                    "_key": "H3 Text",
                                    "_value": "{{image.name}}",
                                    "_type": "a",
                                    "_attrDef": "p"
                                },
                                {
                                    "_key": "id",
                                    "_value": "heading{{image.name}}",
                                    "_type": "kv",
                                    "_attrDef": "c"
                                }
                            ]
                        },
                        "e9dd7191-acd8-e229-005a-a94dcd7d8b1b": {
                            "paletteKey": "FlexLayoutRow",
                            "designerReference": [
                                {
                                    "0": false,
                                    "_key": "style",
                                    "_value": "",
                                    "_type": "kv",
                                    "_attrDef": "p"
                                },
                                {
                                    "1": false,
                                    "_key": "class",
                                    "_value": "",
                                    "_type": "kv",
                                    "_attrDef": "p"
                                },
                                {
                                    "2": true,
                                    "_key": "fxFlex",
                                    "_value": "100",
                                    "_type": "kv",
                                    "_attrDef": "p"
                                },
                                {
                                    "3": false,
                                    "_key": "wrap",
                                    "_value": "wrap",
                                    "_type": "a",
                                    "_attrDef": "p"
                                },
                                {
                                    "4": false,
                                    "_key": "fxLayoutGap",
                                    "_value": "10px",
                                    "_type": "kv",
                                    "_attrDef": "p"
                                },
                                {
                                    "6": false,
                                    "_key": "fxShow",
                                    "_value": "true",
                                    "_type": "kv",
                                    "_attrDef": "p"
                                },
                                {
                                    "7": false,
                                    "_key": "fxHide",
                                    "_value": "false",
                                    "_type": "kv",
                                    "_attrDef": "p"
                                },
                                {
                                    "_key": "layoutAlign",
                                    "_value": " ",
                                    "_type": "a",
                                    "_attrDef": "p"
                                },
                                {
                                    "_key": "pLayoutAlign",
                                    "_value": "none",
                                    "_type": "a",
                                    "_attrDef": "p"
                                }
                            ],
                            "7086f6ba-eadd-2cf9-305d-a3206c984712": {
                                "paletteKey": "FlexLayoutCol",
                                "designerReference": [
                                    {
                                        "0": false,
                                        "_key": "style",
                                        "_value": "",
                                        "_type": "kv",
                                        "_attrDef": "p"
                                    },
                                    {
                                        "1": false,
                                        "_key": "class",
                                        "_value": "",
                                        "_type": "kv",
                                        "_attrDef": "p"
                                    },
                                    {
                                        "2": false,
                                        "_key": "fxFlex",
                                        "_value": "{{zoom}}",
                                        "_type": "kv",
                                        "_attrDef": "p"
                                    },
                                    {
                                        "3": false,
                                        "_key": "wrap",
                                        "_value": "",
                                        "_type": "a",
                                        "_attrDef": "p"
                                    },
                                    {
                                        "4": false,
                                        "_key": "fxLayoutGap",
                                        "_value": "",
                                        "_type": "kv",
                                        "_attrDef": "p"
                                    },
                                    {
                                        "6": false,
                                        "_key": "fxShow",
                                        "_value": "true",
                                        "_type": "kv",
                                        "_attrDef": "p"
                                    },
                                    {
                                        "7": false,
                                        "_key": "fxHide",
                                        "_value": "false",
                                        "_type": "kv",
                                        "_attrDef": "p"
                                    },
                                    {
                                        "8": false,
                                        "9": false,
                                        "_key": "fxFlex.sm",
                                        "_value": "47",
                                        "_type": "kv",
                                        "_attrDef": "c"
                                    },
                                    {
                                        "9": false,
                                        "10": false,
                                        "11": false,
                                        "12": false,
                                        "13": false,
                                        "_key": "fxFlex.xs",
                                        "_value": "100",
                                        "_type": "kv",
                                        "_attrDef": "c"
                                    },
                                    {
                                        "10": false,
                                        "11": false,
                                        "12": false,
                                        "13": false,
                                        "14": false,
                                        "_key": "*ngFor",
                                        "_value": "let img of image.images",
                                        "_type": "kv",
                                        "_attrDef": "c"
                                    },
                                    {
                                        "11": false,
                                        "12": false,
                                        "_key": "fxFlex.gt-md",
                                        "_value": "{{zoom}}",
                                        "_type": "kv",
                                        "_attrDef": "c"
                                    },
                                    {
                                        "12": false,
                                        "_key": "fxFlex.md",
                                        "_value": "{{zoomMd}}",
                                        "_type": "kv",
                                        "_attrDef": "c"
                                    },
                                    {
                                        "_key": "layoutAlign",
                                        "_value": "start",
                                        "_type": "a",
                                        "_attrDef": "p"
                                    },
                                    {
                                        "_key": "pLayoutAlign",
                                        "_value": "stretch",
                                        "_type": "a",
                                        "_attrDef": "p"
                                    }
                                ],
                                "c0678b68-c66a-3a88-76a5-6c95b3db9bde": {
                                    "paletteKey": "HTML",
                                    "designerReference": [
                                        {
                                            "_key": "style",
                                            "_value": "",
                                            "_type": "kv",
                                            "_attrDef": "p"
                                        },
                                        {
                                            "_key": "class",
                                            "_value": "",
                                            "_type": "kv",
                                            "_attrDef": "p"
                                        },
                                        {
                                            "_key": "html",
                                            "_value": "<img class=\"home-images-list\" src=\"{{img.src}}\" (click)=\"onImgClick(img)\" alt=\"{{img.title}}\" title=\"{{img.title}}\">\n",
                                            "_type": "a",
                                            "_attrDef": "p"
                                        }
                                    ]
                                },
                                "3ed4d571-ac27-2983-c142-9816839ab370": {
                                    "paletteKey": "NG-Paragraph",
                                    "designerReference": [
                                        {
                                            "0": false,
                                            "_key": "style",
                                            "_value": "opacity:.5;",
                                            "_type": "kv",
                                            "_attrDef": "p"
                                        },
                                        {
                                            "1": false,
                                            "_key": "class",
                                            "_value": "",
                                            "_type": "kv",
                                            "_attrDef": "p"
                                        },
                                        {
                                            "2": false,
                                            "_key": "text",
                                            "_value": "{{img.title}}",
                                            "_type": "a",
                                            "_attrDef": "p"
                                        },
                                        {
                                            "3": false,
                                            "4": false,
                                            "5": false,
                                            "_key": "[ngStyle.sm]",
                                            "_value": "{'font-size':'10px'}",
                                            "_type": "kv",
                                            "_attrDef": "c"
                                        },
                                        {
                                            "4": false,
                                            "5": false,
                                            "_key": "[ngStyle.xs]",
                                            "_value": "{'font-size':'10px'}",
                                            "_type": "kv",
                                            "_attrDef": "c"
                                        }
                                    ]
                                }
                            }
                        }
                    }
                }
            }
        },
        "91a8b192-1e6b-7e0a-630a-c8c68721aabd": {
            "paletteKey": "NG-Toolbar",
            "designerReference": [
                {
                    "_key": "style",
                    "_value": "    position: fixed !important;     bottom: 0;     z-index: 1;     height: 30px;",
                    "_type": "kv",
                    "_attrDef": "p"
                },
                {
                    "_key": "class",
                    "_value": "",
                    "_type": "kv",
                    "_attrDef": "p"
                },
                {
                    "_key": "color",
                    "_value": "primary",
                    "_type": "kv",
                    "_attrDef": "p"
                },
                {
                    "_key": "content",
                    "_value": "",
                    "_type": "a",
                    "_attrDef": "p"
                }
            ],
            "af27359e-db5a-1bdb-4e48-ac94b505a36d": {
                "paletteKey": "FlexLayoutCol",
                "designerReference": [
                    {
                        "_key": "style",
                        "_value": "",
                        "_type": "kv",
                        "_attrDef": "p"
                    },
                    {
                        "_key": "class",
                        "_value": "",
                        "_type": "kv",
                        "_attrDef": "p"
                    },
                    {
                        "_key": "fxFlex",
                        "_value": "100",
                        "_type": "kv",
                        "_attrDef": "p"
                    },
                    {
                        "_key": "fxLayoutGap",
                        "_value": "",
                        "_type": "kv",
                        "_attrDef": "p"
                    },
                    {
                        "_key": "wrap",
                        "_value": "wrap",
                        "_type": "a",
                        "_attrDef": "p"
                    },
                    {
                        "_key": "layoutAlign",
                        "_value": "center",
                        "_type": "a",
                        "_attrDef": "p"
                    },
                    {
                        "_key": "pLayoutAlign",
                        "_value": "center",
                        "_type": "a",
                        "_attrDef": "p"
                    },
                    {
                        "_key": "fxShow",
                        "_value": "true",
                        "_type": "kv",
                        "_attrDef": "p"
                    },
                    {
                        "_key": "fxHide",
                        "_value": "false",
                        "_type": "kv",
                        "_attrDef": "p"
                    }
                ],
                "3bbb9661-a90e-87e0-b290-f3df784e3ab9": {
                    "paletteKey": "NG-Paragraph",
                    "designerReference": [
                        {
                            "_key": "style",
                            "_value": "font-size:12px",
                            "_type": "kv",
                            "_attrDef": "p"
                        },
                        {
                            "_key": "class",
                            "_value": "",
                            "_type": "kv",
                            "_attrDef": "p"
                        },
                        {
                            "_key": "text",
                            "_value": "&copy; 2018",
                            "_type": "a",
                            "_attrDef": "p"
                        }
                    ]
                }
            }
        }
    }
}
